traffic_light.v
module traffic_light_controller(
    input clk,rst,
    output reg[2:0]light_M1,
    output reg[2:0]light_M2,
    output reg[2:0]light_S,
    output reg[2:0]light_MT
);
parameter s1=0,s2=1,s3=2,s4=3,s5=4,s6=5;
reg[3:0] count;
reg[2:0] ps;
parameter sec7=7,sec5=5,sec2=2,sec3=3;

always@(posedge clk or posedge rst)
begin
if(rst)
begin 
ps<=s1;
count<=4'b0;
end
else
case(ps)
s1:
if(count<sec7)
begin
ps<=s1;
count<=count+1;
end
else
begin
ps<=s2;
count<=0;
end
s2:
if(count<sec2)
begin
ps<=s2;
count<=count+1;
end
else
begin
ps<=s3;
count<=0;
end
s3:
if(count<sec3)
begin
ps<=s3;
count<=count+1;
end
else
begin
ps<=s4;
count<=0;
end
s4:
if(count<sec2)
begin
ps<=s4;
count<=count+1;
end
else
begin
ps<=s5;
count<=0;
end
s5:
if(count<sec3)
begin
ps<=s5;
count<=count+1;
end
else
begin
ps<=s6;
count<=0;
end
s6:
if(count<sec2)
begin
ps<=s6;
count<=count+1;
end
else
begin
ps<=s1;
count<=0;
end
default:ps<=s1;
endcase
end

always@(ps)
begin
case(ps)
s1:
begin
light_M1<=3'b001;
light_M2<=3'b001;
light_MT<=3'b100;
light_S<=3'b100;
end
s2:
begin
light_M1<=3'b001;
light_M2<=3'b010;
light_MT<=3'b100;
light_S<=3'b100;
end
s3:
begin
light_M1<=3'b001;
light_M2<=3'b100;
light_MT<=3'b001;
light_S<=3'b100;
end
s4:
begin
light_M1<=3'b010;
light_M2<=3'b100;
light_MT<=3'b010;
light_S<=3'b100;
end
s5:
begin
light_M1<=3'b100;
light_M2<=3'b100;
light_MT<=3'b100;
light_S<=3'b001;
end
s6:
begin
light_M1<=3'b100;
light_M2<=3'b100;
light_MT<=3'b100;
light_S<=3'b010;
end
default:
begin
light_M1<=3'b100;
light_M2<=3'b100;
light_MT<=3'b100;
light_S<=3'b100;
end
endcase
end
endmodule

traffic_light_tb.v
module traffic_light_tb;
reg clk,rst;
wire[2:0] light_M1;
wire[2:0] light_M2;
wire[2:0] light_S;
wire[2:0] light_MT;
wire[3:0] count;
wire[2:0] ps;

traffic_light_controller dut(.clk(clk),.rst(rst),.light_M1(light_M1),.light_M2(light_M2),.light_MT(light_MT),.light_S(light_S));
initial begin
  clk=1'b1;
  forever #5 clk=~clk;
end

initial begin
  rst=1;
  #20;
  rst=0;
  #3000;
  $finish;
end
initial begin
    $dumpfile("wavetraffic.vcd");
    $dumpvars(0, traffic_light_tb);
end
endmodule

wavetraffic.vcd
$date
	Sun Jun 28 17:45:26 2026
$end
$version
	Icarus Verilog
$end
$timescale
	1s
$end
$scope module traffic_light_tb $end
$var wire 3 ! light_S [2:0] $end
$var wire 3 " light_MT [2:0] $end
$var wire 3 # light_M2 [2:0] $end
$var wire 3 $ light_M1 [2:0] $end
$var reg 1 % clk $end
$var reg 1 & rst $end
$scope module dut $end
$var wire 1 % clk $end
$var wire 1 & rst $end
$var parameter 32 ' s1 $end
$var parameter 32 ( s2 $end
$var parameter 32 ) s3 $end
$var parameter 32 * s4 $end
$var parameter 32 + s5 $end
$var parameter 32 , s6 $end
$var parameter 32 - sec2 $end
$var parameter 32 . sec3 $end
$var parameter 32 / sec5 $end
$var parameter 32 0 sec7 $end
$var reg 4 1 count [3:0] $end
$var reg 3 2 light_M1 [2:0] $end
$var reg 3 3 light_M2 [2:0] $end
$var reg 3 4 light_MT [2:0] $end
$var reg 3 5 light_S [2:0] $end
$var reg 3 6 ps [2:0] $end
$upscope $end
$upscope $end
$enddefinitions $end
$comment Show the parameter values. $end
$dumpall
b111 0
b101 /
b11 .
b10 -
b101 ,
b100 +
b11 *
b10 )
b1 (
b0 '
$end
#0
$dumpvars
b0 6
b100 5
b100 4
b1 3
b1 2
b0 1
1&
1%
b1 $
b1 #
b100 "
b100 !
$end
#5
0%
#10
1%
#15
0%
#20
b1 1
1%
0&
#25
0%
#30
b10 1
1%
#35
0%
#40
b11 1
1%
#45
0%
#50
b100 1
1%
#55
0%
#60
b101 1
1%
#65
0%
#70
b110 1
1%
#75
0%
#80
b111 1
1%
#85
0%
#90
b10 #
b10 3
b0 1
b1 6
1%
#95
0%
#100
b1 1
1%
#105
0%
#110
b10 1
1%
#115
0%
#120
b1 "
b1 4
b100 #
b100 3
b0 1
b10 6
1%
#125
0%
#130
b1 1
1%
#135
0%
#140
b10 1
1%
#145
0%
#150
b11 1
1%
#155
0%
#160
b10 "
b10 4
b10 $
b10 2
b0 1
b11 6
1%
#165
0%
#170
b1 1
1%
#175
0%
#180
b10 1
1%
#185
0%
#190
b1 !
b1 5
b100 "
b100 4
b100 $
b100 2
b0 1
b100 6
1%
#195
0%
#200
b1 1
1%
#205
0%
#210
b10 1
1%
#215
0%
#220
b11 1
1%
#225
0%
#230
b10 !
b10 5
b0 1
b101 6
1%
#235
0%
#240
b1 1
1%
#245
0%
#250
b10 1
1%
#255
0%
#260
b100 !
b100 5
b1 #
b1 3
b1 $
b1 2
b0 1
b0 6
1%
#265
0%
#270
b1 1
1%
#275
0%
#280
b10 1
1%
#285
0%
#290
b11 1
1%
#295
0%
#300
b100 1
1%
#305
0%
#310
b101 1
1%
#315
0%
#320
b110 1
1%
#325
0%
#330
b111 1
1%
#335
0%
#340
b10 #
b10 3
b0 1
b1 6
1%
#345
0%
#350
b1 1
1%
#355
0%
#360
b10 1
1%
#365
0%
#370
b1 "
b1 4
b100 #
b100 3
b0 1
b10 6
1%
#375
0%
#380
b1 1
1%
#385
0%
#390
b10 1
1%
#395
0%
#400
b11 1
1%
#405
0%
#410
b10 "
b10 4
b10 $
b10 2
b0 1
b11 6
1%
#415
0%
#420
b1 1
1%
#425
0%
#430
b10 1
1%
#435
0%
#440
b1 !
b1 5
b100 "
b100 4
b100 $
b100 2
b0 1
b100 6
1%
#445
0%
#450
b1 1
1%
#455
0%
#460
b10 1
1%
#465
0%
#470
b11 1
1%
#475
0%
#480
b10 !
b10 5
b0 1
b101 6
1%
#485
0%
#490
b1 1
1%
#495
0%
#500
b10 1
1%
#505
0%
#510
b100 !
b100 5
b1 #
b1 3
b1 $
b1 2
b0 1
b0 6
1%
#515
0%
#520
b1 1
1%
#525
0%
#530
b10 1
1%
#535
0%
#540
b11 1
1%
#545
0%
#550
b100 1
1%
#555
0%
#560
b101 1
1%
#565
0%
#570
b110 1
1%
#575
0%
#580
b111 1
1%
#585
0%
#590
b10 #
b10 3
b0 1
b1 6
1%
#595
0%
#600
b1 1
1%
#605
0%
#610
b10 1
1%
#615
0%
#620
b1 "
b1 4
b100 #
b100 3
b0 1
b10 6
1%
#625
0%
#630
b1 1
1%
#635
0%
#640
b10 1
1%
#645
0%
#650
b11 1
1%
#655
0%
#660
b10 "
b10 4
b10 $
b10 2
b0 1
b11 6
1%
#665
0%
#670
b1 1
1%
#675
0%
#680
b10 1
1%
#685
0%
#690
b1 !
b1 5
b100 "
b100 4
b100 $
b100 2
b0 1
b100 6
1%
#695
0%
#700
b1 1
1%
#705
0%
#710
b10 1
1%
#715
0%
#720
b11 1
1%
#725
0%
#730
b10 !
b10 5
b0 1
b101 6
1%
#735
0%
#740
b1 1
1%
#745
0%
#750
b10 1
1%
#755
0%
#760
b100 !
b100 5
b1 #
b1 3
b1 $
b1 2
b0 1
b0 6
1%
#765
0%
#770
b1 1
1%
#775
0%
#780
b10 1
1%
#785
0%
#790
b11 1
1%
#795
0%
#800
b100 1
1%
#805
0%
#810
b101 1
1%
#815
0%
#820
b110 1
1%
#825
0%
#830
b111 1
1%
#835
0%
#840
b10 #
b10 3
b0 1
b1 6
1%
#845
0%
#850
b1 1
1%
#855
0%
#860
b10 1
1%
#865
0%
#870
b1 "
b1 4
b100 #
b100 3
b0 1
b10 6
1%
#875
0%
#880
b1 1
1%
#885
0%
#890
b10 1
1%
#895
0%
#900
b11 1
1%
#905
0%
#910
b10 "
b10 4
b10 $
b10 2
b0 1
b11 6
1%
#915
0%
#920
b1 1
1%
#925
0%
#930
b10 1
1%
#935
0%
#940
b1 !
b1 5
b100 "
b100 4
b100 $
b100 2
b0 1
b100 6
1%
#945
0%
#950
b1 1
1%
#955
0%
#960
b10 1
1%
#965
0%
#970
b11 1
1%
#975
0%
#980
b10 !
b10 5
b0 1
b101 6
1%
#985
0%
#990
b1 1
1%
#995
0%
#1000
b10 1
1%
#1005
0%
#1010
b100 !
b100 5
b1 #
b1 3
b1 $
b1 2
b0 1
b0 6
1%
#1015
0%
#1020
b1 1
1%
#1025
0%
#1030
b10 1
1%
#1035
0%
#1040
b11 1
1%
#1045
0%
#1050
b100 1
1%
#1055
0%
#1060
b101 1
1%
#1065
0%
#1070
b110 1
1%
#1075
0%
#1080
b111 1
1%
#1085
0%
#1090
b10 #
b10 3
b0 1
b1 6
1%
#1095
0%
#1100
b1 1
1%
#1105
0%
#1110
b10 1
1%
#1115
0%
#1120
b1 "
b1 4
b100 #
b100 3
b0 1
b10 6
1%
#1125
0%
#1130
b1 1
1%
#1135
0%
#1140
b10 1
1%
#1145
0%
#1150
b11 1
1%
#1155
0%
#1160
b10 "
b10 4
b10 $
b10 2
b0 1
b11 6
1%
#1165
0%
#1170
b1 1
1%
#1175
0%
#1180
b10 1
1%
#1185
0%
#1190
b1 !
b1 5
b100 "
b100 4
b100 $
b100 2
b0 1
b100 6
1%
#1195
0%
#1200
b1 1
1%
#1205
0%
#1210
b10 1
1%
#1215
0%
#1220
b11 1
1%
#1225
0%
#1230
b10 !
b10 5
b0 1
b101 6
1%
#1235
0%
#1240
b1 1
1%
#1245
0%
#1250
b10 1
1%
#1255
0%
#1260
b100 !
b100 5
b1 #
b1 3
b1 $
b1 2
b0 1
b0 6
1%
#1265
0%
#1270
b1 1
1%
#1275
0%
#1280
b10 1
1%
#1285
0%
#1290
b11 1
1%
#1295
0%
#1300
b100 1
1%
#1305
0%
#1310
b101 1
1%
#1315
0%
#1320
b110 1
1%
#1325
0%
#1330
b111 1
1%
#1335
0%
#1340
b10 #
b10 3
b0 1
b1 6
1%
#1345
0%
#1350
b1 1
1%
#1355
0%
#1360
b10 1
1%
#1365
0%
#1370
b1 "
b1 4
b100 #
b100 3
b0 1
b10 6
1%
#1375
0%
#1380
b1 1
1%
#1385
0%
#1390
b10 1
1%
#1395
0%
#1400
b11 1
1%
#1405
0%
#1410
b10 "
b10 4
b10 $
b10 2
b0 1
b11 6
1%
#1415
0%
#1420
b1 1
1%
#1425
0%
#1430
b10 1
1%
#1435
0%
#1440
b1 !
b1 5
b100 "
b100 4
b100 $
b100 2
b0 1
b100 6
1%
#1445
0%
#1450
b1 1
1%
#1455
0%
#1460
b10 1
1%
#1465
0%
#1470
b11 1
1%
#1475
0%
#1480
b10 !
b10 5
b0 1
b101 6
1%
#1485
0%
#1490
b1 1
1%
#1495
0%
#1500
b10 1
1%
#1505
0%
#1510
b100 !
b100 5
b1 #
b1 3
b1 $
b1 2
b0 1
b0 6
1%
#1515
0%
#1520
b1 1
1%
#1525
0%
#1530
b10 1
1%
#1535
0%
#1540
b11 1
1%
#1545
0%
#1550
b100 1
1%
#1555
0%
#1560
b101 1
1%
#1565
0%
#1570
b110 1
1%
#1575
0%
#1580
b111 1
1%
#1585
0%
#1590
b10 #
b10 3
b0 1
b1 6
1%
#1595
0%
#1600
b1 1
1%
#1605
0%
#1610
b10 1
1%
#1615
0%
#1620
b1 "
b1 4
b100 #
b100 3
b0 1
b10 6
1%
#1625
0%
#1630
b1 1
1%
#1635
0%
#1640
b10 1
1%
#1645
0%
#1650
b11 1
1%
#1655
0%
#1660
b10 "
b10 4
b10 $
b10 2
b0 1
b11 6
1%
#1665
0%
#1670
b1 1
1%
#1675
0%
#1680
b10 1
1%
#1685
0%
#1690
b1 !
b1 5
b100 "
b100 4
b100 $
b100 2
b0 1
b100 6
1%
#1695
0%
#1700
b1 1
1%
#1705
0%
#1710
b10 1
1%
#1715
0%
#1720
b11 1
1%
#1725
0%
#1730
b10 !
b10 5
b0 1
b101 6
1%
#1735
0%
#1740
b1 1
1%
#1745
0%
#1750
b10 1
1%
#1755
0%
#1760
b100 !
b100 5
b1 #
b1 3
b1 $
b1 2
b0 1
b0 6
1%
#1765
0%
#1770
b1 1
1%
#1775
0%
#1780
b10 1
1%
#1785
0%
#1790
b11 1
1%
#1795
0%
#1800
b100 1
1%
#1805
0%
#1810
b101 1
1%
#1815
0%
#1820
b110 1
1%
#1825
0%
#1830
b111 1
1%
#1835
0%
#1840
b10 #
b10 3
b0 1
b1 6
1%
#1845
0%
#1850
b1 1
1%
#1855
0%
#1860
b10 1
1%
#1865
0%
#1870
b1 "
b1 4
b100 #
b100 3
b0 1
b10 6
1%
#1875
0%
#1880
b1 1
1%
#1885
0%
#1890
b10 1
1%
#1895
0%
#1900
b11 1
1%
#1905
0%
#1910
b10 "
b10 4
b10 $
b10 2
b0 1
b11 6
1%
#1915
0%
#1920
b1 1
1%
#1925
0%
#1930
b10 1
1%
#1935
0%
#1940
b1 !
b1 5
b100 "
b100 4
b100 $
b100 2
b0 1
b100 6
1%
#1945
0%
#1950
b1 1
1%
#1955
0%
#1960
b10 1
1%
#1965
0%
#1970
b11 1
1%
#1975
0%
#1980
b10 !
b10 5
b0 1
b101 6
1%
#1985
0%
#1990
b1 1
1%
#1995
0%
#2000
b10 1
1%
#2005
0%
#2010
b100 !
b100 5
b1 #
b1 3
b1 $
b1 2
b0 1
b0 6
1%
#2015
0%
#2020
b1 1
1%
#2025
0%
#2030
b10 1
1%
#2035
0%
#2040
b11 1
1%
#2045
0%
#2050
b100 1
1%
#2055
0%
#2060
b101 1
1%
#2065
0%
#2070
b110 1
1%
#2075
0%
#2080
b111 1
1%
#2085
0%
#2090
b10 #
b10 3
b0 1
b1 6
1%
#2095
0%
#2100
b1 1
1%
#2105
0%
#2110
b10 1
1%
#2115
0%
#2120
b1 "
b1 4
b100 #
b100 3
b0 1
b10 6
1%
#2125
0%
#2130
b1 1
1%
#2135
0%
#2140
b10 1
1%
#2145
0%
#2150
b11 1
1%
#2155
0%
#2160
b10 "
b10 4
b10 $
b10 2
b0 1
b11 6
1%
#2165
0%
#2170
b1 1
1%
#2175
0%
#2180
b10 1
1%
#2185
0%
#2190
b1 !
b1 5
b100 "
b100 4
b100 $
b100 2
b0 1
b100 6
1%
#2195
0%
#2200
b1 1
1%
#2205
0%
#2210
b10 1
1%
#2215
0%
#2220
b11 1
1%
#2225
0%
#2230
b10 !
b10 5
b0 1
b101 6
1%
#2235
0%
#2240
b1 1
1%
#2245
0%
#2250
b10 1
1%
#2255
0%
#2260
b100 !
b100 5
b1 #
b1 3
b1 $
b1 2
b0 1
b0 6
1%
#2265
0%
#2270
b1 1
1%
#2275
0%
#2280
b10 1
1%
#2285
0%
#2290
b11 1
1%
#2295
0%
#2300
b100 1
1%
#2305
0%
#2310
b101 1
1%
#2315
0%
#2320
b110 1
1%
#2325
0%
#2330
b111 1
1%
#2335
0%
#2340
b10 #
b10 3
b0 1
b1 6
1%
#2345
0%
#2350
b1 1
1%
#2355
0%
#2360
b10 1
1%
#2365
0%
#2370
b1 "
b1 4
b100 #
b100 3
b0 1
b10 6
1%
#2375
0%
#2380
b1 1
1%
#2385
0%
#2390
b10 1
1%
#2395
0%
#2400
b11 1
1%
#2405
0%
#2410
b10 "
b10 4
b10 $
b10 2
b0 1
b11 6
1%
#2415
0%
#2420
b1 1
1%
#2425
0%
#2430
b10 1
1%
#2435
0%
#2440
b1 !
b1 5
b100 "
b100 4
b100 $
b100 2
b0 1
b100 6
1%
#2445
0%
#2450
b1 1
1%
#2455
0%
#2460
b10 1
1%
#2465
0%
#2470
b11 1
1%
#2475
0%
#2480
b10 !
b10 5
b0 1
b101 6
1%
#2485
0%
#2490
b1 1
1%
#2495
0%
#2500
b10 1
1%
#2505
0%
#2510
b100 !
b100 5
b1 #
b1 3
b1 $
b1 2
b0 1
b0 6
1%
#2515
0%
#2520
b1 1
1%
#2525
0%
#2530
b10 1
1%
#2535
0%
#2540
b11 1
1%
#2545
0%
#2550
b100 1
1%
#2555
0%
#2560
b101 1
1%
#2565
0%
#2570
b110 1
1%
#2575
0%
#2580
b111 1
1%
#2585
0%
#2590
b10 #
b10 3
b0 1
b1 6
1%
#2595
0%
#2600
b1 1
1%
#2605
0%
#2610
b10 1
1%
#2615
0%
#2620
b1 "
b1 4
b100 #
b100 3
b0 1
b10 6
1%
#2625
0%
#2630
b1 1
1%
#2635
0%
#2640
b10 1
1%
#2645
0%
#2650
b11 1
1%
#2655
0%
#2660
b10 "
b10 4
b10 $
b10 2
b0 1
b11 6
1%
#2665
0%
#2670
b1 1
1%
#2675
0%
#2680
b10 1
1%
#2685
0%
#2690
b1 !
b1 5
b100 "
b100 4
b100 $
b100 2
b0 1
b100 6
1%
#2695
0%
#2700
b1 1
1%
#2705
0%
#2710
b10 1
1%
#2715
0%
#2720
b11 1
1%
#2725
0%
#2730
b10 !
b10 5
b0 1
b101 6
1%
#2735
0%
#2740
b1 1
1%
#2745
0%
#2750
b10 1
1%
#2755
0%
#2760
b100 !
b100 5
b1 #
b1 3
b1 $
b1 2
b0 1
b0 6
1%
#2765
0%
#2770
b1 1
1%
#2775
0%
#2780
b10 1
1%
#2785
0%
#2790
b11 1
1%
#2795
0%
#2800
b100 1
1%
#2805
0%
#2810
b101 1
1%
#2815
0%
#2820
b110 1
1%
#2825
0%
#2830
b111 1
1%
#2835
0%
#2840
b10 #
b10 3
b0 1
b1 6
1%
#2845
0%
#2850
b1 1
1%
#2855
0%
#2860
b10 1
1%
#2865
0%
#2870
b1 "
b1 4
b100 #
b100 3
b0 1
b10 6
1%
#2875
0%
#2880
b1 1
1%
#2885
0%
#2890
b10 1
1%
#2895
0%
#2900
b11 1
1%
#2905
0%
#2910
b10 "
b10 4
b10 $
b10 2
b0 1
b11 6
1%
#2915
0%
#2920
b1 1
1%
#2925
0%
#2930
b10 1
1%
#2935
0%
#2940
b1 !
b1 5
b100 "
b100 4
b100 $
b100 2
b0 1
b100 6
1%
#2945
0%
#2950
b1 1
1%
#2955
0%
#2960
b10 1
1%
#2965
0%
#2970
b11 1
1%
#2975
0%
#2980
b10 !
b10 5
b0 1
b101 6
1%
#2985
0%
#2990
b1 1
1%
#2995
0%
#3000
b10 1
1%
#3005
0%
#3010
b100 !
b100 5
b1 #
b1 3
b1 $
b1 2
b0 1
b0 6
1%
#3015
0%
#3020
b1 1
1%
